CHANGES.rst
LICENSE.txt
MANIFEST.in
README.rst
RELEASE-VERSION
setup.py
version.py
staticdocs_plugin.egg-info/PKG-INFO
staticdocs_plugin.egg-info/SOURCES.txt
staticdocs_plugin.egg-info/dependency_links.txt
staticdocs_plugin.egg-info/entry_points.txt
staticdocs_plugin.egg-info/requires.txt
staticdocs_plugin.egg-info/top_level.txt
staticdocs_plugin.egg-info/zip-safe
staticdocsplugin/__init__.py
staticdocsplugin/staticdocs.py
staticdocsplugin/test.py