Metadata-Version: 1.0
Name: staticdocs-plugin
Version: 0.1
Summary: A Trac plugin to allow access to static documents
Home-page: http://github.com/dairiki/staticdocs-plugin
Author: Jeff Dairiki
Author-email: dairiki@dairiki.org
License: BSD
Keywords: trac
Platform: Any
Classifier: Development Status :: 4 - Beta
Classifier: Environment :: Plugins
Classifier: Environment :: Web Environment
Classifier: Framework :: Trac
Classifier: Intended Audience :: System Administrators
Classifier: Topic :: Internet :: WWW/HTTP
Classifier: Programming Language :: Python :: 2
Classifier: License :: OSI Approved :: BSD License
